{
  "brand": "Ferri",
  "models": [
    {
      "model": "Mtb vers FerriBike",
      "type": "Crosscountry",
      "ebike": false,
      "suspension": "hardtail",
      "sizes": [
        {
          "size": "M",
          "rider_height_min": 163,
          "rider_height_max": 178,
          "measurement_unit": "cm"
        }
      ]
    },
    {
      "model": "FR",
      "type": "Road",
      "ebike": false,
      "suspension": null,
      "sizes": [
        {
          "size": "S",
          "rider_height_min": 158,
          "rider_height_max": 173,
          "measurement_unit": "cm"
        }
      ]
    }
  ]
}