{
  "brand": "Kross",
  "models": [
    {
      "model": "ESKER 2.0",
      "type": "Gravel",
      "ebike": false,
      "suspension": "rigid",
      "sizes": [
        {
          "size": null,
          "rider_height_min": 168,
          "rider_height_max": 178,
          "measurement_unit": "cm"
        }
      ]
    },
    {
      "model": "LEVEL 4.0",
      "type": "Crosscountry",
      "ebike": false,
      "suspension": "hardtail",
      "sizes": [
        {
          "size": "M",
          "rider_height_min": 163,
          "rider_height_max": 178,
          "measurement_unit": "cm"
        }
      ]
    },
    {
      "model": "LEVEL 7.0 LADY",
      "type": "Crosscountry",
      "ebike": false,
      "suspension": "hardtail",
      "sizes": [
        {
          "size": "M",
          "rider_height_min": 163,
          "rider_height_max": 178,
          "measurement_unit": "cm"
        }
      ]
    },
    {
      "model": "EARTH 3.0 2023",
      "type": "Crosscountry",
      "ebike": false,
      "suspension": "full",
      "sizes": [
        {
          "size": "S",
          "rider_height_min": 158,
          "rider_height_max": 173,
          "measurement_unit": "cm"
        }
      ]
    },
    {
      "model": "VENTO 8.0",
      "type": "Road",
      "ebike": false,
      "suspension": null,
      "sizes": [
        {
          "size": "XL",
          "rider_height_min": 178,
          "rider_height_max": 198,
          "measurement_unit": "cm"
        }
      ]
    },
    {
      "model": "HEXAGON 5.0",
      "type": "Crosscountry",
      "ebike": false,
      "suspension": "hardtail",
      "sizes": [
        {
          "size": "M",
          "rider_height_min": 163,
          "rider_height_max": 178,
          "measurement_unit": "cm"
        }
      ]
    },
    {
      "model": "ESKER 7.0",
      "type": "Gravel",
      "ebike": false,
      "suspension": null,
      "sizes": [
        {
          "size": "S",
          "rider_height_min": 158,
          "rider_height_max": 173,
          "measurement_unit": "cm"
        }
      ]
    },
    {
      "model": "Kross Level 2.0",
      "type": "Crosscountry",
      "ebike": false,
      "suspension": "hardtail",
      "sizes": [
        {
          "size": "L",
          "rider_height_min": 173,
          "rider_height_max": 188,
          "measurement_unit": "cm"
        }
      ]
    },
    {
      "model": "Level 2.0 PW",
      "type": "Crosscountry",
      "ebike": false,
      "suspension": "hardtail",
      "sizes": [
        {
          "size": "S",
          "rider_height_min": 158,
          "rider_height_max": 173,
          "measurement_unit": "cm"
        }
      ]
    },
    {
      "model": "B4",
      "type": "Crosscountry",
      "ebike": false,
      "suspension": "hardtail",
      "sizes": [
        {
          "size": "XL",
          "rider_height_min": 178,
          "rider_height_max": 198,
          "measurement_unit": "cm"
        }
      ]
    },
    {
      "model": "EARTH TE",
      "type": "Crosscountry",
      "ebike": false,
      "suspension": "full",
      "sizes": [
        {
          "size": "M",
          "rider_height_min": 163,
          "rider_height_max": 178,
          "measurement_unit": "cm"
        },
        {
          "size": null,
          "rider_height_min": 168,
          "rider_height_max": 178,
          "measurement_unit": "cm"
        }
      ]
    },
    {
      "model": "ESKER 8.0 2023",
      "type": "Gravel",
      "ebike": false,
      "suspension": null,
      "sizes": [
        {
          "size": null,
          "rider_height_min": 168,
          "rider_height_max": 178,
          "measurement_unit": "cm"
        }
      ]
    },
    {
      "model": "Black edition 2",
      "type": "Downhill",
      "ebike": false,
      "suspension": "hardtail",
      "sizes": [
        {
          "size": null,
          "rider_height_min": 147,
          "rider_height_max": 163,
          "measurement_unit": "cm"
        }
      ]
    },
    {
      "model": "VENTO 2.0",
      "type": "Road",
      "ebike": false,
      "suspension": "rigid",
      "sizes": [
        {
          "size": "S",
          "rider_height_min": 185,
          "rider_height_max": 195,
          "measurement_unit": "cm"
        }
      ]
    },
    {
      "model": "ESKER 1.0",
      "type": "Gravel",
      "ebike": false,
      "suspension": "rigid",
      "sizes": [
        {
          "size": "M",
          "rider_height_min": 163,
          "rider_height_max": 178,
          "measurement_unit": "cm"
        },
        {
          "size": "L",
          "rider_height_min": 168,
          "rider_height_max": 180,
          "measurement_unit": "cm"
        },
        {
          "size": "S",
          "rider_height_min": 186,
          "rider_height_max": 199,
          "measurement_unit": "cm"
        }
      ]
    },
    {
      "model": "MOON 1.0",
      "type": "Enduro",
      "ebike": false,
      "suspension": "full",
      "sizes": [
        {
          "size": "S",
          "rider_height_min": 158,
          "rider_height_max": 173,
          "measurement_unit": "cm"
        }
      ]
    },
    {
      "model": "6.0",
      "type": "Road",
      "ebike": false,
      "suspension": null,
      "sizes": [
        {
          "size": null,
          "rider_height_min": 168,
          "rider_height_max": 178,
          "measurement_unit": "cm"
        }
      ]
    },
    {
      "model": "LEVEL 2.0",
      "type": "Crosscountry",
      "ebike": false,
      "suspension": "hardtail",
      "sizes": [
        {
          "size": "M",
          "rider_height_min": 163,
          "rider_height_max": 178,
          "measurement_unit": "cm"
        }
      ]
    },
    {
      "model": "EARTH 2.0",
      "type": "Downhill",
      "ebike": false,
      "suspension": "full",
      "sizes": [
        {
          "size": "XL",
          "rider_height_min": 178,
          "rider_height_max": 198,
          "measurement_unit": "cm"
        }
      ]
    },
    {
      "model": "LEVEL 7.0",
      "type": "Crosscountry",
      "ebike": false,
      "suspension": "hardtail",
      "sizes": [
        {
          "size": "L",
          "rider_height_min": 178,
          "rider_height_max": 189,
          "measurement_unit": "cm"
        }
      ]
    },
    {
      "model": "ESKER 6.0",
      "type": "Gravel",
      "ebike": false,
      "suspension": null,
      "sizes": [
        {
          "size": "XL",
          "rider_height_min": 168,
          "rider_height_max": 180,
          "measurement_unit": "cm"
        }
      ]
    },
    {
      "model": "VENTO 5.0",
      "type": "Road",
      "ebike": false,
      "suspension": null,
      "sizes": [
        {
          "size": "M",
          "rider_height_min": 156,
          "rider_height_max": 166,
          "measurement_unit": "cm"
        }
      ]
    },
    {
      "model": "Mtb KROSS 24",
      "type": "Crosscountry",
      "ebike": false,
      "suspension": "hardtail",
      "sizes": [
        {
          "size": "XXS",
          "rider_height_min": 147,
          "rider_height_max": 163,
          "measurement_unit": "cm"
        }
      ]
    },
    {
      "model": "ESKER 4.0",
      "type": "Gravel",
      "ebike": false,
      "suspension": null,
      "sizes": [
        {
          "size": "XL",
          "rider_height_min": 178,
          "rider_height_max": 198,
          "measurement_unit": "cm"
        }
      ]
    },
    {
      "model": "HEXAGON 7.0",
      "type": "Crosscountry",
      "ebike": false,
      "suspension": "hardtail",
      "sizes": [
        {
          "size": "XL",
          "rider_height_min": 186,
          "rider_height_max": 199,
          "measurement_unit": "cm"
        }
      ]
    },
    {
      "model": "MS_BLACK EDITION_2",
      "type": "Trail",
      "ebike": false,
      "suspension": "rigid",
      "sizes": [
        {
          "size": "M",
          "rider_height_min": 163,
          "rider_height_max": 178,
          "measurement_unit": "cm"
        }
      ]
    },
    {
      "model": "EARTH 3.0",
      "type": "Crosscountry",
      "ebike": false,
      "suspension": "full",
      "sizes": [
        {
          "size": "M",
          "rider_height_min": 163,
          "rider_height_max": 178,
          "measurement_unit": "cm"
        }
      ]
    },
    {
      "model": "HEXAGON 3.0",
      "type": "Crosscountry",
      "ebike": false,
      "suspension": "rigid",
      "sizes": [
        {
          "size": "M",
          "rider_height_min": 163,
          "rider_height_max": 178,
          "measurement_unit": "cm"
        }
      ]
    }
  ]
}